{
    "e7jzy9z": [
        {
            "Parent ID": "t3_9mxsh9",
            "Comment ID": "e7jzy9z",
            "Author": "OscarsNoseBeers",
            "Date Created": "10-10-2018 23:37:29",
            "Upvotes": 8,
            "Text": "Liquid seems sick, Lightning keeps picking up momentum, and institutional buyers keep gaining new avenues to enter the market.\n\nWho cares about the price, Bitcoin is becoming stronger by the day. It's becoming more usable, and the next halvening is getting closer - prices will rise again eventually.",
            "Edited?": false,
            "Is Submitter?": false,
            "Stickied?": false
        }
    ],
    "e7k2d8r": [
        {
            "Parent ID": "t3_9mxsh9",
            "Comment ID": "e7k2d8r",
            "Author": "[deleted]",
            "Date Created": "10-11-2018 00:25:50",
            "Upvotes": 9,
            "Text": "[deleted]",
            "Edited?": false,
            "Is Submitter?": false,
            "Stickied?": false
        }
    ],
    "e7jvmpn": [
        {
            "Parent ID": "t3_9mxsh9",
            "Comment ID": "e7jvmpn",
            "Author": "dejesuswho808",
            "Date Created": "10-10-2018 22:21:19",
            "Upvotes": 6,
            "Text": "Hodl me",
            "Edited?": false,
            "Is Submitter?": false,
            "Stickied?": false
        }
    ],
    "e7j1ysg": [
        {
            "Parent ID": "t3_9mxsh9",
            "Comment ID": "e7j1ysg",
            "Author": "[deleted]",
            "Date Created": "10-10-2018 14:49:14",
            "Upvotes": 4,
            "Text": "[deleted]",
            "Edited?": false,
            "Is Submitter?": false,
            "Stickied?": false
        }
    ],
    "e7jvv9v": [
        {
            "Parent ID": "t3_9mxsh9",
            "Comment ID": "e7jvv9v",
            "Author": "coloured_sunglasses",
            "Date Created": "10-10-2018 22:25:18",
            "Upvotes": 5,
            "Text": "One sell triggers many bots to sell. This has happened many times up and down. \n\nAlso the charts exaggerate the selloff due to little movement in the last month. Compare it to the selloff in September, it's nothing.",
            "Edited?": false,
            "Is Submitter?": false,
            "Stickied?": false
        }
    ],
    "e7jxek5": [
        {
            "Parent ID": "t3_9mxsh9",
            "Comment ID": "e7jxek5",
            "Author": "ProctoKopf",
            "Date Created": "10-10-2018 22:51:24",
            "Upvotes": 5,
            "Text": "Nothing to see here. Normal middle of the month drop. Move along.",
            "Edited?": false,
            "Is Submitter?": false,
            "Stickied?": false
        }
    ],
    "e7ib80u": [
        {
            "Parent ID": "t3_9mxsh9",
            "Comment ID": "e7ib80u",
            "Author": "crayzcrinkle",
            "Date Created": "10-10-2018 08:18:11",
            "Upvotes": 3,
            "Text": "Buy the dip! I am going to try using gdax later if it's still below \u00a35,000!",
            "Edited?": false,
            "Is Submitter?": false,
            "Stickied?": false
        }
    ],
    "e7iw9j2": [
        {
            "Parent ID": "t3_9mxsh9",
            "Comment ID": "e7iw9j2",
            "Author": "[deleted]",
            "Date Created": "10-10-2018 13:32:18",
            "Upvotes": 3,
            "Text": "[deleted]",
            "Edited?": false,
            "Is Submitter?": false,
            "Stickied?": false
        }
    ],
    "e7jszbe": [
        {
            "Parent ID": "t3_9mxsh9",
            "Comment ID": "e7jszbe",
            "Author": "Jason1189",
            "Date Created": "10-10-2018 21:36:16",
            "Upvotes": 3,
            "Text": "I was expecting a fall on crypto after today's stock market action. People might panic in Crypto market over the stock market. Lucky the 6050 level holds, we should be ok from free fall.",
            "Edited?": false,
            "Is Submitter?": false,
            "Stickied?": false
        }
    ],
    "e7k1132": [
        {
            "Parent ID": "t3_9mxsh9",
            "Comment ID": "e7k1132",
            "Author": "blockchaincasino",
            "Date Created": "10-10-2018 23:58:22",
            "Upvotes": 3,
            "Text": "Whoweee!  Who just slipped on the soap?",
            "Edited?": false,
            "Is Submitter?": false,
            "Stickied?": false
        }
    ],
    "e7j4vio": [
        {
            "Parent ID": "t3_9mxsh9",
            "Comment ID": "e7j4vio",
            "Author": "[deleted]",
            "Date Created": "10-10-2018 15:28:15",
            "Upvotes": 7,
            "Text": "[deleted]",
            "Edited?": "10-10-2018 15:36:19",
            "Is Submitter?": false,
            "Stickied?": false
        }
    ],
    "e7jvl5x": [
        {
            "Parent ID": "t3_9mxsh9",
            "Comment ID": "e7jvl5x",
            "Author": "ray3400",
            "Date Created": "10-10-2018 22:20:36",
            "Upvotes": 2,
            "Text": "why is it dipping?",
            "Edited?": false,
            "Is Submitter?": false,
            "Stickied?": false
        }
    ],
    "e7k9gwm": [
        {
            "Parent ID": "t3_9mxsh9",
            "Comment ID": "e7k9gwm",
            "Author": "crayzcrinkle",
            "Date Created": "10-11-2018 03:29:48",
            "Upvotes": 2,
            "Text": "Anxiously waiting for my fiat to clear onto GDAX and hoping I don't miss this ticket! This looks like a buy signal to me.",
            "Edited?": false,
            "Is Submitter?": false,
            "Stickied?": false
        }
    ],
    "e7kblft": [
        {
            "Parent ID": "t3_9mxsh9",
            "Comment ID": "e7kblft",
            "Author": "Muyan93",
            "Date Created": "10-11-2018 04:45:28",
            "Upvotes": 2,
            "Text": "Just buy 0.2 at 6100. #iamdoingmypart",
            "Edited?": false,
            "Is Submitter?": false,
            "Stickied?": false
        }
    ],
    "e7jlzqc": [
        {
            "Parent ID": "t3_9mxsh9",
            "Comment ID": "e7jlzqc",
            "Author": "LemosineRidin",
            "Date Created": "10-10-2018 19:38:59",
            "Upvotes": 2,
            "Text": "Go home. Run a hot bath and rinse this shit off your ass. Then buy a couple more coins ",
            "Edited?": false,
            "Is Submitter?": false,
            "Stickied?": false
        }
    ],
    "e7jdgp7": [
        {
            "Parent ID": "t3_9mxsh9",
            "Comment ID": "e7jdgp7",
            "Author": "[deleted]",
            "Date Created": "10-10-2018 17:26:11",
            "Upvotes": 3,
            "Text": "Sold all my coin today, going traveling need the $$ \n\nwill buy back in a month :)",
            "Edited?": false,
            "Is Submitter?": false,
            "Stickied?": false
        }
    ],
    "e7jw82n": [
        {
            "Parent ID": "t3_9mxsh9",
            "Comment ID": "e7jw82n",
            "Author": "[deleted]",
            "Date Created": "10-10-2018 22:31:16",
            "Upvotes": 3,
            "Text": "I'm glad crypto is a good store of value. It only lost 5% today...compared to 3% on the stock market.",
            "Edited?": false,
            "Is Submitter?": false,
            "Stickied?": false
        }
    ],
    "e7jdsa6": [
        {
            "Parent ID": "t3_9mxsh9",
            "Comment ID": "e7jdsa6",
            "Author": "arBettor",
            "Date Created": "10-10-2018 17:30:44",
            "Upvotes": 4,
            "Text": "Bitcoin displayed its lack of correlation with stocks today.  \n\nAlso, for those who like to get Bitcoin exposure in retirement accounts, GBTC fell 5.4% today while BTC dropped less than 1%.  That premium to its NAV is getting pretty thin.  It's not for everyone obviously, but for those who can carve off a piece of their exposure and leave it in Grayscale's custody, now's probably as good a time as any.",
            "Edited?": false,
            "Is Submitter?": false,
            "Stickied?": false
        }
    ],
    "e7iwvl0": [
        {
            "Parent ID": "t3_9mxsh9",
            "Comment ID": "e7iwvl0",
            "Author": "55555",
            "Date Created": "10-10-2018 13:40:35",
            "Upvotes": 2,
            "Text": "Fucking hell. Either go up so I can profit from what I bought so far, or go down so I can buy more. Been hovering at my break-even point for 6 months now. So fucking bored.",
            "Edited?": false,
            "Is Submitter?": false,
            "Stickied?": false
        }
    ],
    "e7ju7vh": [
        {
            "Parent ID": "t3_9mxsh9",
            "Comment ID": "e7ju7vh",
            "Author": "warlord85",
            "Date Created": "10-10-2018 21:57:29",
            "Upvotes": 2,
            "Text": "( ( ( ( ( HODL ) ) ) ) )",
            "Edited?": false,
            "Is Submitter?": false,
            "Stickied?": false
        }
    ],
    "e7jupmu": [
        {
            "Parent ID": "t3_9mxsh9",
            "Comment ID": "e7jupmu",
            "Author": "Suprdave123",
            "Date Created": "10-10-2018 22:05:59",
            "Upvotes": 2,
            "Text": "It's like someone pushed a button and gapped down the entire crypto market at once...",
            "Edited?": false,
            "Is Submitter?": false,
            "Stickied?": false
        }
    ],
    "e7jy6x9": [
        {
            "Parent ID": "t3_9mxsh9",
            "Comment ID": "e7jy6x9",
            "Author": "the_real_johnybutton",
            "Date Created": "10-10-2018 23:04:59",
            "Upvotes": 2,
            "Text": "Why so scared ppl! The entire **\"Market Cap\"** 1st support level (from here) is around the early 200'sb area anyway...if it breaks than the next is around 189-190'sb area (bottom so far). Unless your a day gambler, go to the beach & relax, get a misses and practice baby making",
            "Edited?": false,
            "Is Submitter?": false,
            "Stickied?": false
        }
    ],
    "e7juiyt": [
        {
            "Parent ID": "t3_9mxsh9",
            "Comment ID": "e7juiyt",
            "Author": "Icantw8",
            "Date Created": "10-10-2018 22:02:50",
            "Upvotes": 2,
            "Text": "This market is cancer.",
            "Edited?": false,
            "Is Submitter?": false,
            "Stickied?": false
        }
    ],
    "e7id8lc": [
        {
            "Parent ID": "t3_9mxsh9",
            "Comment ID": "e7id8lc",
            "Author": "Iruwen",
            "Date Created": "10-10-2018 08:57:38",
            "Upvotes": 1,
            "Text": "https://i.imgur.com/bWcWmJM.png\n\nWhatever is messing up arbitrage currently, funniest one here is Bittrex' USD and USDT pairs.",
            "Edited?": false,
            "Is Submitter?": false,
            "Stickied?": false
        }
    ],
    "e7jryyr": [
        {
            "Parent ID": "t3_9mxsh9",
            "Comment ID": "e7jryyr",
            "Author": "cipher-space",
            "Date Created": "10-10-2018 21:19:15",
            "Upvotes": 1,
            "Text": "Looks like somebody lookin to jumpstart the ol volatility engine ya?",
            "Edited?": false,
            "Is Submitter?": false,
            "Stickied?": false
        }
    ],
    "e7j9faj": [
        {
            "Parent ID": "t3_9mxsh9",
            "Comment ID": "e7j9faj",
            "Author": "[deleted]",
            "Date Created": "10-10-2018 16:29:37",
            "Upvotes": 2,
            "Text": "[deleted]",
            "Edited?": false,
            "Is Submitter?": false,
            "Stickied?": false
        }
    ],
    "e7i5jl9": [
        {
            "Parent ID": "t3_9mxsh9",
            "Comment ID": "e7i5jl9",
            "Author": "[deleted]",
            "Date Created": "10-10-2018 05:40:02",
            "Upvotes": 1,
            "Text": "[deleted]",
            "Edited?": false,
            "Is Submitter?": false,
            "Stickied?": false
        }
    ],
    "e7j2usm": [
        {
            "Parent ID": "t3_9mxsh9",
            "Comment ID": "e7j2usm",
            "Author": "supplyantsimon",
            "Date Created": "10-10-2018 15:01:10",
            "Upvotes": 1,
            "Text": "Tech stocks (in fact most) have been battered over the last few days. Come on over to the dark side of BTC where the price of bitcoin barely moves...",
            "Edited?": false,
            "Is Submitter?": false,
            "Stickied?": false
        }
    ],
    "e7jsofd": [
        {
            "Parent ID": "t3_9mxsh9",
            "Comment ID": "e7jsofd",
            "Author": "ZealotCloud",
            "Date Created": "10-10-2018 21:31:11",
            "Upvotes": 1,
            "Text": "Bears on some bathsalts right now",
            "Edited?": false,
            "Is Submitter?": false,
            "Stickied?": false
        }
    ],
    "e7juww4": [
        {
            "Parent ID": "t3_9mxsh9",
            "Comment ID": "e7juww4",
            "Author": "Mrvice18",
            "Date Created": "10-10-2018 22:09:23",
            "Upvotes": 1,
            "Text": "I regret not selling a few when market was at 8000 or 10000 a couple of months ago. Why is it dipping all of a sudden",
            "Edited?": false,
            "Is Submitter?": false,
            "Stickied?": false
        }
    ],
    "e7jrqf1": [
        {
            "Parent ID": "t3_9mxsh9",
            "Comment ID": "e7jrqf1",
            "Author": "ZealotCloud",
            "Date Created": "10-10-2018 21:15:12",
            "Upvotes": 1,
            "Text": "Feeling that massive reversal hammer coming",
            "Edited?": false,
            "Is Submitter?": false,
            "Stickied?": false
        }
    ],
    "e7js4oc": [
        {
            "Parent ID": "t3_9mxsh9",
            "Comment ID": "e7js4oc",
            "Author": "cryptogiraffewins",
            "Date Created": "10-10-2018 21:21:55",
            "Upvotes": 1,
            "Text": "Retesting $6200. Let\u2019s see if the bottom is the bottom. Or if me can drop more.",
            "Edited?": false,
            "Is Submitter?": false,
            "Stickied?": false
        }
    ],
    "e7kbr0p": [
        {
            "Parent ID": "t3_9mxsh9",
            "Comment ID": "e7kbr0p",
            "Author": "FintechMining",
            "Date Created": "10-11-2018 04:51:07",
            "Upvotes": 1,
            "Text": "Its unpredictable!!",
            "Edited?": false,
            "Is Submitter?": false,
            "Stickied?": false
        }
    ],
    "e7jtido": [
        {
            "Parent ID": "t3_9mxsh9",
            "Comment ID": "e7jtido",
            "Author": "RIMS_REAL_BIG",
            "Date Created": "10-10-2018 21:45:20",
            "Upvotes": 0,
            "Text": "Crypto is a joke. ",
            "Edited?": false,
            "Is Submitter?": false,
            "Stickied?": false
        }
    ],
    "e7iq455": [
        {
            "Parent ID": "t3_9mxsh9",
            "Comment ID": "e7iq455",
            "Author": "[deleted]",
            "Date Created": "10-10-2018 12:08:37",
            "Upvotes": -2,
            "Text": "[deleted]",
            "Edited?": false,
            "Is Submitter?": false,
            "Stickied?": false
        }
    ],
    "e7jtz0y": [
        {
            "Parent ID": "t3_9mxsh9",
            "Comment ID": "e7jtz0y",
            "Author": "[deleted]",
            "Date Created": "10-10-2018 21:53:16",
            "Upvotes": 0,
            "Text": "[removed]",
            "Edited?": "10-11-2018 03:01:09",
            "Is Submitter?": false,
            "Stickied?": false
        }
    ],
    "e7i5dqi": [
        {
            "Parent ID": "t3_9mxsh9",
            "Comment ID": "e7i5dqi",
            "Author": "[deleted]",
            "Date Created": "10-10-2018 05:34:12",
            "Upvotes": -1,
            "Text": "I have a feeling that this dump will recover completely and turn into a enmourmus Jesus candle",
            "Edited?": false,
            "Is Submitter?": false,
            "Stickied?": false
        }
    ],
    "e7jj37e": [
        {
            "Parent ID": "t3_9mxsh9",
            "Comment ID": "e7jj37e",
            "Author": "crypto_hustler",
            "Date Created": "10-10-2018 18:51:21",
            "Upvotes": 0,
            "Text": "https://www.ccn.com/breaking-harvard-stanford-mit-have-all-invested-in-cryptocurrency-funds/",
            "Edited?": false,
            "Is Submitter?": false,
            "Stickied?": false
        }
    ],
    "e7jvcag": [
        {
            "Parent ID": "t3_9mxsh9",
            "Comment ID": "e7jvcag",
            "Author": "Neveragain646",
            "Date Created": "10-10-2018 22:16:30",
            "Upvotes": 0,
            "Text": "It's almost impossible to go lower than 5500. Price follows the interest. Interest is at 7 out of 100 (in december). Lowest point in 16 months. But you need an interest level of 5 to go under 5500, which is unlikely to happen so quickly (maybe in 2 months). Numbers are based on google trend. Price follows the interest. Number one basic economic rule. 5500 is the new bottom based on the interest though.",
            "Edited?": false,
            "Is Submitter?": false,
            "Stickied?": false
        }
    ],
    "e7jsaes": [
        {
            "Parent ID": "t3_9mxsh9",
            "Comment ID": "e7jsaes",
            "Author": "crypto_hustler",
            "Date Created": "10-10-2018 21:24:36",
            "Upvotes": 1,
            "Text": "we are gonna drop below $6k in a few min",
            "Edited?": false,
            "Is Submitter?": false,
            "Stickied?": false
        }
    ],
    "e7iff9v": [
        {
            "Parent ID": "t3_9mxsh9",
            "Comment ID": "e7iff9v",
            "Author": "bandezzzzz",
            "Date Created": "10-10-2018 09:34:32",
            "Upvotes": -5,
            "Text": "Patiently waiting for the next batch of greater fools.",
            "Edited?": false,
            "Is Submitter?": false,
            "Stickied?": false
        }
    ],
    "e7iam9y": [
        {
            "Parent ID": "t3_9mxsh9",
            "Comment ID": "e7iam9y",
            "Author": "Valency1",
            "Date Created": "10-10-2018 08:05:40",
            "Upvotes": -1,
            "Text": "Google sure knows\n\n[https://zycrypto.com/revealed-what-google-really-thinks-of-bitcoin-and-cryptocurrencies/](https://zycrypto.com/revealed-what-google-really-thinks-of-bitcoin-and-cryptocurrencies/)",
            "Edited?": false,
            "Is Submitter?": false,
            "Stickied?": false
        }
    ],
    "e7ilwqr": [
        {
            "Parent ID": "t3_9mxsh9",
            "Comment ID": "e7ilwqr",
            "Author": "teddykolarov1004",
            "Date Created": "10-10-2018 11:10:45",
            "Upvotes": -1,
            "Text": "What do you guys thing about Tether blowing up or is that old news and just FUD?",
            "Edited?": false,
            "Is Submitter?": false,
            "Stickied?": false
        }
    ],
    "e7jv1dr": [
        {
            "Parent ID": "t3_9mxsh9",
            "Comment ID": "e7jv1dr",
            "Author": "lavazzalove",
            "Date Created": "10-10-2018 22:11:29",
            "Upvotes": -1,
            "Text": "To be honest, I'm impressed. Haven't seen this type of price action before across major cryptocurrenncies.",
            "Edited?": false,
            "Is Submitter?": false,
            "Stickied?": false
        }
    ],
    "e7jrju7": [
        {
            "Parent ID": "t3_9mxsh9",
            "Comment ID": "e7jrju7",
            "Author": "crypto_hustler",
            "Date Created": "10-10-2018 21:12:02",
            "Upvotes": 0,
            "Text": "got stopped out@$6350....yikes",
            "Edited?": false,
            "Is Submitter?": false,
            "Stickied?": false
        }
    ],
    "e7jrkw8": [
        {
            "Parent ID": "t3_9mxsh9",
            "Comment ID": "e7jrkw8",
            "Author": "crypto_hustler",
            "Date Created": "10-10-2018 21:12:33",
            "Upvotes": 0,
            "Text": "$6180 on cb pro",
            "Edited?": false,
            "Is Submitter?": false,
            "Stickied?": false
        }
    ],
    "e7jryhk": [
        {
            "Parent ID": "t3_9mxsh9",
            "Comment ID": "e7jryhk",
            "Author": "Taimoorrana",
            "Date Created": "10-10-2018 21:19:02",
            "Upvotes": 0,
            "Text": "What just happened??? So much bear volume",
            "Edited?": false,
            "Is Submitter?": false,
            "Stickied?": false
        }
    ],
    "e7jysuj": [
        {
            "Parent ID": "t3_9mxsh9",
            "Comment ID": "e7jysuj",
            "Author": "[deleted]",
            "Date Created": "10-10-2018 23:16:01",
            "Upvotes": -3,
            "Text": "DOW dropped 3% so they are cashing out some btc to offset the lose. \n\nThis is GOOD cause it puts more bitcoin into circulation from the whales who HODL. The more the they sell, the more bitcoin gets to people who want it (and at discount). ",
            "Edited?": false,
            "Is Submitter?": false,
            "Stickied?": false
        }
    ],
    "e7jooqy": [
        {
            "Parent ID": "t3_9mxsh9",
            "Comment ID": "e7jooqy",
            "Author": "Neveragain646",
            "Date Created": "10-10-2018 20:24:07",
            "Upvotes": -4,
            "Text": "The price follows the interest (not the other way around ofcourse). Interest is at the score of 7 out of 100 (december) right now. The lowest score in 16 months. The only positive thing is, it Wlwill probably not go down much more. You have to wait for a new economic crisis, and then 2 or 3 more years before btc goes up to 20.000 again. Could take 6-10 years.",
            "Edited?": false,
            "Is Submitter?": false,
            "Stickied?": false
        }
    ],
    "e7jrvz5": [
        {
            "Parent ID": "t3_9mxsh9",
            "Comment ID": "e7jrvz5",
            "Author": "crypto_hustler",
            "Date Created": "10-10-2018 21:17:51",
            "Upvotes": -1,
            "Text": "tether @$.983....tether insolvency fud causing this dip ?",
            "Edited?": false,
            "Is Submitter?": false,
            "Stickied?": false
        }
    ],
    "e7jxhaq": [
        {
            "Parent ID": "t3_9mxsh9",
            "Comment ID": "e7jxhaq",
            "Author": "xelephonte",
            "Date Created": "10-10-2018 22:52:41",
            "Upvotes": -14,
            "Text": "But Cryptogrip and the Physicist promised Bakkt would resurrect Bitcoin for good. Ahahaha cryptogrip has no grip on anything. Bitcoin $2900 by Jan. 2019. Mark my words.",
            "Edited?": false,
            "Is Submitter?": false,
            "Stickied?": false
        }
    ],
    "e7k5yfd": [
        {
            "Parent ID": "t1_e7k2d8r",
            "Comment ID": "e7k5yfd",
            "Author": "whalecheetah",
            "Date Created": "10-11-2018 01:48:41",
            "Upvotes": 3,
            "Text": "Totally. The pattern has repeated multiple times. They seem to Target days where people are more susceptible . like today when Wall Street sold off really hard and we had some new tether fud. Large holder dumps out and starts a waterfall downward. More people jump in and at that point he can buy his coins back cheaper",
            "Edited?": false,
            "Is Submitter?": false,
            "Stickied?": false
        }
    ],
    "e7kgpoy": [
        {
            "Parent ID": "t1_e7k2d8r",
            "Comment ID": "e7kgpoy",
            "Author": "ray3400",
            "Date Created": "10-11-2018 07:28:23",
            "Upvotes": 1,
            "Text": "&#x200B;\n\nThere was a 15k BTC transfer on the ledger around the time it happened yesterday, not sure if it is related.\n\n[https://www.blockchain.com/btc/address/35gwu76KvShhjg2SQdFcH6caC2MBFyXk75](https://www.blockchain.com/btc/address/35gwu76KvShhjg2SQdFcH6caC2MBFyXk75)",
            "Edited?": false,
            "Is Submitter?": false,
            "Stickied?": false
        }
    ],
    "e7jpwjv": [
        {
            "Parent ID": "t1_e7j1ysg",
            "Comment ID": "e7jpwjv",
            "Author": "Raphman90",
            "Date Created": "10-10-2018 20:44:21",
            "Upvotes": 1,
            "Text": "I live so close to there now. I should make the trip up sometime",
            "Edited?": false,
            "Is Submitter?": false,
            "Stickied?": false
        }
    ],
    "e7jx8vi": [
        {
            "Parent ID": "t1_e7jvv9v",
            "Comment ID": "e7jx8vi",
            "Author": "flunderbossanova",
            "Date Created": "10-10-2018 22:48:38",
            "Upvotes": -2,
            "Text": "are those sunglasses rose colored?",
            "Edited?": false,
            "Is Submitter?": false,
            "Stickied?": false
        }
    ],
    "e7jx9io": [
        {
            "Parent ID": "t1_e7ib80u",
            "Comment ID": "e7jx9io",
            "Author": "xelephonte",
            "Date Created": "10-10-2018 22:48:56",
            "Upvotes": -2,
            "Text": "Who the hell are you talking in Euros? Who does that? And please don\u2019t respond calling me mate... I am not your mate. Either talk in dollars or don\u2019t talk at all...or talk in yen but definitely not euros.",
            "Edited?": false,
            "Is Submitter?": false,
            "Stickied?": false
        }
    ],
    "e7ix4cs": [
        {
            "Parent ID": "t1_e7iw9j2",
            "Comment ID": "e7ix4cs",
            "Author": "55555",
            "Date Created": "10-10-2018 13:43:55",
            "Upvotes": 3,
            "Text": "ACH transfers from your bank. Deposit to cash wallet on coinbase, transfer to gdax, limit buy. 0 Fees.",
            "Edited?": false,
            "Is Submitter?": false,
            "Stickied?": false
        }
    ],
    "e7iz3t2": [
        {
            "Parent ID": "t1_e7iw9j2",
            "Comment ID": "e7iz3t2",
            "Author": "cryptogrip",
            "Date Created": "10-10-2018 14:10:51",
            "Upvotes": 3,
            "Text": "In Canada? Shakepay is probably the easiest way. You just install the app, verified instantly with your cell number, then e-transfer funds and buy BTC or ETH. Then you can cold storage it or send to wherever you like. Even keep on the app if it's a small amount.",
            "Edited?": false,
            "Is Submitter?": false,
            "Stickied?": false
        }
    ],
    "e7jtr6z": [
        {
            "Parent ID": "t1_e7jszbe",
            "Comment ID": "e7jtr6z",
            "Author": "flunderbossanova",
            "Date Created": "10-10-2018 21:49:30",
            "Upvotes": 1,
            "Text": "I doubt this has anything to do with the stock market. My money is on Tether/Bitfinex insolvency rumors.",
            "Edited?": false,
            "Is Submitter?": false,
            "Stickied?": false
        }
    ],
    "e7k3lkf": [
        {
            "Parent ID": "t1_e7k1132",
            "Comment ID": "e7k3lkf",
            "Author": "Spykwak",
            "Date Created": "10-11-2018 00:52:24",
            "Upvotes": 1,
            "Text": "At least volume is up now :-)",
            "Edited?": false,
            "Is Submitter?": false,
            "Stickied?": false
        }
    ],
    "e7j8fbp": [
        {
            "Parent ID": "t1_e7j4vio",
            "Comment ID": "e7j8fbp",
            "Author": "[deleted]",
            "Date Created": "10-10-2018 16:16:04",
            "Upvotes": -6,
            "Text": "[deleted]",
            "Edited?": false,
            "Is Submitter?": false,
            "Stickied?": false
        }
    ],
    "e7jyc38": [
        {
            "Parent ID": "t1_e7jvl5x",
            "Comment ID": "e7jyc38",
            "Author": "the_real_johnybutton",
            "Date Created": "10-10-2018 23:07:33",
            "Upvotes": 1,
            "Text": "here is a great read on how rich whales manipulate the market. Using stocks as the example, same applies here, Step by Step. Just google this (i dont know if i get introuble for sharing a direct link): the secret trading strategy from 1930's",
            "Edited?": false,
            "Is Submitter?": false,
            "Stickied?": false
        }
    ],
    "e7jxfc0": [
        {
            "Parent ID": "t1_e7jvl5x",
            "Comment ID": "e7jxfc0",
            "Author": "tbonecollion",
            "Date Created": "10-10-2018 22:51:45",
            "Upvotes": 1,
            "Text": "Because they want me to buy more at a discounted rate.",
            "Edited?": false,
            "Is Submitter?": false,
            "Stickied?": false
        }
    ],
    "e7jw1bh": [
        {
            "Parent ID": "t1_e7jvl5x",
            "Comment ID": "e7jw1bh",
            "Author": "Neveragain646",
            "Date Created": "10-10-2018 22:28:07",
            "Upvotes": -5,
            "Text": "Because interest is at lowest point in 16 months. It dropped from 10 to 7 on a scale of 100 from august to now. Bitcoin's value was too high for two months. Now it corrected to what it should have been. ",
            "Edited?": false,
            "Is Submitter?": false,
            "Stickied?": false
        }
    ],
    "e7k9ixe": [
        {
            "Parent ID": "t1_e7k9gwm",
            "Comment ID": "e7k9ixe",
            "Author": "[deleted]",
            "Date Created": "10-11-2018 03:31:42",
            "Upvotes": 2,
            "Text": "Instant deposit USD to coinbase then transfer to GDAX there\u2019s no waiting period",
            "Edited?": false,
            "Is Submitter?": false,
            "Stickied?": false
        }
    ],
    "e7kbcce": [
        {
            "Parent ID": "t1_e7k9gwm",
            "Comment ID": "e7kbcce",
            "Author": "Spykwak",
            "Date Created": "10-11-2018 04:36:21",
            "Upvotes": 1,
            "Text": "Same, waiting for my SEPA payement to go trough :-)",
            "Edited?": false,
            "Is Submitter?": false,
            "Stickied?": false
        }
    ],
    "e7jxztk": [
        {
            "Parent ID": "t1_e7jlzqc",
            "Comment ID": "e7jxztk",
            "Author": "repkjund",
            "Date Created": "10-10-2018 23:01:31",
            "Upvotes": 0,
            "Text": "indeed ! the big dildo is about to come",
            "Edited?": false,
            "Is Submitter?": false,
            "Stickied?": false
        }
    ],
    "e7jpko1": [
        {
            "Parent ID": "t1_e7jdgp7",
            "Comment ID": "e7jpko1",
            "Author": "FlyGuy74",
            "Date Created": "10-10-2018 20:38:50",
            "Upvotes": 4,
            "Text": "Sell low, buy high \ud83d\udc4d\ud83c\udffc",
            "Edited?": false,
            "Is Submitter?": false,
            "Stickied?": false
        }
    ],
    "e7jrxxy": [
        {
            "Parent ID": "t1_e7jdgp7",
            "Comment ID": "e7jrxxy",
            "Author": "Nemesis207",
            "Date Created": "10-10-2018 21:18:47",
            "Upvotes": 1,
            "Text": "good call. perfect timing.",
            "Edited?": false,
            "Is Submitter?": false,
            "Stickied?": false
        }
    ],
    "e7jg9q6": [
        {
            "Parent ID": "t1_e7jdsa6",
            "Comment ID": "e7jg9q6",
            "Author": "cryptogrip",
            "Date Created": "10-10-2018 18:07:21",
            "Upvotes": 6,
            "Text": "Today was absolutely brutal for stocks. I am not sure the last time I saw Amazon drop that much in a day. I had more inquiries about purchasing bitcoin today than I've had in the past few months combined. If this is any sign,  bitcoin will hold well in a recession. But I am not happy about the stocks lol.",
            "Edited?": false,
            "Is Submitter?": false,
            "Stickied?": false
        }
    ],
    "e7jrpjn": [
        {
            "Parent ID": "t1_e7jdsa6",
            "Comment ID": "e7jrpjn",
            "Author": "RIMS_REAL_BIG",
            "Date Created": "10-10-2018 21:14:47",
            "Upvotes": 7,
            "Text": "You were saying? ",
            "Edited?": false,
            "Is Submitter?": false,
            "Stickied?": false
        }
    ],
    "e7jzs20": [
        {
            "Parent ID": "t1_e7jdsa6",
            "Comment ID": "e7jzs20",
            "Author": "Light_of_Lucifer",
            "Date Created": "10-10-2018 23:34:11",
            "Upvotes": 0,
            "Text": "Spoke to early",
            "Edited?": false,
            "Is Submitter?": false,
            "Stickied?": false
        }
    ],
    "e7jxb0u": [
        {
            "Parent ID": "t1_e7jdsa6",
            "Comment ID": "e7jxb0u",
            "Author": "xelephonte",
            "Date Created": "10-10-2018 22:49:39",
            "Upvotes": -1,
            "Text": "Hahahajah arbettor way off",
            "Edited?": false,
            "Is Submitter?": false,
            "Stickied?": false
        }
    ],
    "e7jfr4i": [
        {
            "Parent ID": "t1_e7jdsa6",
            "Comment ID": "e7jfr4i",
            "Author": "flunderbossanova",
            "Date Created": "10-10-2018 17:59:33",
            "Upvotes": -2,
            "Text": "Sandwiches are also uncorrelated to stocks",
            "Edited?": false,
            "Is Submitter?": false,
            "Stickied?": false
        }
    ],
    "e7jt9i9": [
        {
            "Parent ID": "t1_e7iwvl0",
            "Comment ID": "e7jt9i9",
            "Author": "slugur",
            "Date Created": "10-10-2018 21:41:09",
            "Upvotes": 5,
            "Text": "Wish granted. ",
            "Edited?": false,
            "Is Submitter?": false,
            "Stickied?": false
        }
    ],
    "e7ixli7": [
        {
            "Parent ID": "t1_e7iwvl0",
            "Comment ID": "e7ixli7",
            "Author": "Spykwak",
            "Date Created": "10-10-2018 13:50:24",
            "Upvotes": 1,
            "Text": "We\u2019re hovering 5% below my break-even point :-( I\u2019m not in the mood to throw good money after bad to lower my break-even point because I\u2019m buying a house atm and I wish to decrease my exposure if possible concerning crypto.\n\n Count yourself lucky :-)\n\n\n\n",
            "Edited?": false,
            "Is Submitter?": false,
            "Stickied?": false
        }
    ],
    "e7jj6ol": [
        {
            "Parent ID": "t1_e7iwvl0",
            "Comment ID": "e7jj6ol",
            "Author": "sabiansoldier",
            "Date Created": "10-10-2018 18:52:50",
            "Upvotes": 1,
            "Text": "11 year old detected",
            "Edited?": false,
            "Is Submitter?": false,
            "Stickied?": false
        }
    ],
    "e7juhdn": [
        {
            "Parent ID": "t1_e7ju7vh",
            "Comment ID": "e7juhdn",
            "Author": "ZealotCloud",
            "Date Created": "10-10-2018 22:02:04",
            "Upvotes": 0,
            "Text": "\"In the arms of the angels\"",
            "Edited?": false,
            "Is Submitter?": false,
            "Stickied?": false
        }
    ],
    "e7juweh": [
        {
            "Parent ID": "t1_e7jupmu",
            "Comment ID": "e7juweh",
            "Author": "flunderbossanova",
            "Date Created": "10-10-2018 22:09:09",
            "Upvotes": 1,
            "Text": "damp eet",
            "Edited?": false,
            "Is Submitter?": false,
            "Stickied?": false
        }
    ],
    "e7k5hrv": [
        {
            "Parent ID": "t1_e7juiyt",
            "Comment ID": "e7k5hrv",
            "Author": "cyrilbenson47",
            "Date Created": "10-11-2018 01:36:58",
            "Upvotes": 0,
            "Text": "it's STD.",
            "Edited?": false,
            "Is Submitter?": false,
            "Stickied?": false
        }
    ],
    "e7je7rh": [
        {
            "Parent ID": "t1_e7j9faj",
            "Comment ID": "e7je7rh",
            "Author": "[deleted]",
            "Date Created": "10-10-2018 17:37:03",
            "Upvotes": 0,
            "Text": "release the kraken",
            "Edited?": false,
            "Is Submitter?": false,
            "Stickied?": false
        }
    ],
    "e7i6lr9": [
        {
            "Parent ID": "t1_e7i5jl9",
            "Comment ID": "e7i6lr9",
            "Author": "lesterdesa",
            "Date Created": "10-10-2018 06:17:05",
            "Upvotes": -1,
            "Text": "lol",
            "Edited?": false,
            "Is Submitter?": false,
            "Stickied?": false
        }
    ],
    "e7jzpcp": [
        {
            "Parent ID": "t1_e7jsofd",
            "Comment ID": "e7jzpcp",
            "Author": "Light_of_Lucifer",
            "Date Created": "10-10-2018 23:32:47",
            "Upvotes": 0,
            "Text": "lol funny af",
            "Edited?": false,
            "Is Submitter?": false,
            "Stickied?": false
        }
    ],
    "e7jzbvx": [
        {
            "Parent ID": "t1_e7juww4",
            "Comment ID": "e7jzbvx",
            "Author": "whalecheetah",
            "Date Created": "10-10-2018 23:25:42",
            "Upvotes": 3,
            "Text": "I don't know if you have been watching the books but bids got pulled. My personal guess is they knew people would be panicking a little bit since Wall Street sold off so hard. If you pull the bids then the Panic sellers keep driving the price lower. Once that is over you turn the bids back on and purchase at lower prices. Give it a few days to see what happens but right now it's pretty constructive. We made a low that was higher than the last low and rebounded pretty well off of it. Now you just watch and wait to see if the low we made a couple hours ago holds",
            "Edited?": false,
            "Is Submitter?": false,
            "Stickied?": false
        }
    ],
    "e7jswjg": [
        {
            "Parent ID": "t1_e7jrqf1",
            "Comment ID": "e7jswjg",
            "Author": "pbahiense",
            "Date Created": "10-10-2018 21:34:58",
            "Upvotes": 0,
            "Text": "haha nice.",
            "Edited?": false,
            "Is Submitter?": false,
            "Stickied?": false
        }
    ],
    "e7jywtt": [
        {
            "Parent ID": "t1_e7js4oc",
            "Comment ID": "e7jywtt",
            "Author": "curseknight",
            "Date Created": "10-10-2018 23:18:04",
            "Upvotes": 1,
            "Text": "This bottom is pretty bottom looking. If this bottom isn't the bottom, what is the bottom? XD",
            "Edited?": false,
            "Is Submitter?": false,
            "Stickied?": false
        }
    ],
    "e7js8ac": [
        {
            "Parent ID": "t1_e7js4oc",
            "Comment ID": "e7js8ac",
            "Author": "ekhasm88",
            "Date Created": "10-10-2018 21:23:37",
            "Upvotes": -2,
            "Text": "the bottom is never the bottom",
            "Edited?": false,
            "Is Submitter?": false,
            "Stickied?": false
        }
    ],
    "e7jtxcv": [
        {
            "Parent ID": "t1_e7jtido",
            "Comment ID": "e7jtxcv",
            "Author": "The-Physicist",
            "Date Created": "10-10-2018 21:52:27",
            "Upvotes": 7,
            "Text": "Not to the people who bought sub $1000 just a couple short years ago  ",
            "Edited?": false,
            "Is Submitter?": false,
            "Stickied?": false
        }
    ],
    "e7jysoi": [
        {
            "Parent ID": "t1_e7jtido",
            "Comment ID": "e7jysoi",
            "Author": "curseknight",
            "Date Created": "10-10-2018 23:15:56",
            "Upvotes": 3,
            "Text": "Yeah, it's a joke. Which means staying here is a complete waste of time to you, right? So, you know what to do!",
            "Edited?": false,
            "Is Submitter?": false,
            "Stickied?": false
        }
    ],
    "e7iq9az": [
        {
            "Parent ID": "t1_e7iq455",
            "Comment ID": "e7iq9az",
            "Author": "crypto_hustler",
            "Date Created": "10-10-2018 12:10:38",
            "Upvotes": 4,
            "Text": "wat ? lol",
            "Edited?": false,
            "Is Submitter?": false,
            "Stickied?": false
        }
    ],
    "e7ju6lr": [
        {
            "Parent ID": "t1_e7jtz0y",
            "Comment ID": "e7ju6lr",
            "Author": "flunderbossanova",
            "Date Created": "10-10-2018 21:56:52",
            "Upvotes": 8,
            "Text": "$20.000 maybe",
            "Edited?": false,
            "Is Submitter?": false,
            "Stickied?": false
        }
    ],
    "e7jyyjn": [
        {
            "Parent ID": "t1_e7jvcag",
            "Comment ID": "e7jyyjn",
            "Author": "the_real_johnybutton",
            "Date Created": "10-10-2018 23:18:56",
            "Upvotes": 5,
            "Text": "If you think to create interest, it will have to be news to beat last years media retail push...after all its the retailers that pushed us to $20k. When media outlets & morning shows start covering BTC again saying \"Breaking! this week BTC become institutional\"...we will have new interest / investors on top of Wall Street, not this stuff we are carrying on about atm, this is petty talk in comparison",
            "Edited?": false,
            "Is Submitter?": false,
            "Stickied?": false
        }
    ],
    "e7jsk4y": [
        {
            "Parent ID": "t1_e7jsaes",
            "Comment ID": "e7jsk4y",
            "Author": "riyau_32",
            "Date Created": "10-10-2018 21:29:10",
            "Upvotes": 2,
            "Text": "I looked it up on google, but no answers why its going down...",
            "Edited?": false,
            "Is Submitter?": false,
            "Stickied?": false
        }
    ],
    "e7jsqtl": [
        {
            "Parent ID": "t1_e7jsaes",
            "Comment ID": "e7jsqtl",
            "Author": "The-Physicist",
            "Date Created": "10-10-2018 21:32:17",
            "Upvotes": 2,
            "Text": "Why couldn\u2019t this have waited to happen until end of month when I\u2019ll actually have money?",
            "Edited?": "10-10-2018 21:38:20",
            "Is Submitter?": false,
            "Stickied?": false
        }
    ],
    "e7iiqaz": [
        {
            "Parent ID": "t1_e7iff9v",
            "Comment ID": "e7iiqaz",
            "Author": "damchi",
            "Date Created": "10-10-2018 10:25:46",
            "Upvotes": 3,
            "Text": "I take it you're buying gold then? Or \"investing\" in stocks (only to sell if/when they go up in your desired percentage)?",
            "Edited?": false,
            "Is Submitter?": false,
            "Stickied?": false
        }
    ],
    "e7irem2": [
        {
            "Parent ID": "t1_e7ilwqr",
            "Comment ID": "e7irem2",
            "Author": "flunderbossanova",
            "Date Created": "10-10-2018 12:26:24",
            "Upvotes": 2,
            "Text": "The spread between Coinbase and Bitfinex keeps getting larger. It's also down to $0.9865 on Kraken. Not saying this is necessarily it, but eventually something will bring their house of cards down.",
            "Edited?": false,
            "Is Submitter?": false,
            "Stickied?": false
        }
    ],
    "e7iwgzq": [
        {
            "Parent ID": "t1_e7ilwqr",
            "Comment ID": "e7iwgzq",
            "Author": "purpurato",
            "Date Created": "10-10-2018 13:35:04",
            "Upvotes": 1,
            "Text": "There is a clear issue with Tether, you can see detailed info on Bitfinexed account on twitter. Bitfinex has never done a proper audit of their accounts and there are some 2.8 billions hole. Something clear is what [flunderbossanova](https://www.reddit.com/user/flunderbossanova) says about the spread, it's getting larger every day and at some point it might start to create panic on the market. ",
            "Edited?": false,
            "Is Submitter?": false,
            "Stickied?": false
        }
    ],
    "e7jtkh9": [
        {
            "Parent ID": "t1_e7jryhk",
            "Comment ID": "e7jtkh9",
            "Author": "bathdweller",
            "Date Created": "10-10-2018 21:46:19",
            "Upvotes": -1,
            "Text": "I think short sellers have found their ceiling has lowered hence the flatlining. They were hoping it would go to 7.5 for a quick win but it ran out of puff. They're all selling off so that they can buy in with a lower baseline and start the game again.",
            "Edited?": false,
            "Is Submitter?": false,
            "Stickied?": false
        }
    ],
    "e7k1qww": [
        {
            "Parent ID": "t1_e7jysuj",
            "Comment ID": "e7k1qww",
            "Author": "[deleted]",
            "Date Created": "10-11-2018 00:12:57",
            "Upvotes": 2,
            "Text": "It doesn't change the amount of bitcoin in circulation.",
            "Edited?": false,
            "Is Submitter?": false,
            "Stickied?": false
        }
    ],
    "e7k6035": [
        {
            "Parent ID": "t1_e7jysuj",
            "Comment ID": "e7k6035",
            "Author": "aidanlister",
            "Date Created": "10-11-2018 01:49:56",
            "Upvotes": 1,
            "Text": "Ah yes, there it is ... \"this is good for bitcoin\"",
            "Edited?": false,
            "Is Submitter?": false,
            "Stickied?": false
        }
    ],
    "e7jr3hf": [
        {
            "Parent ID": "t1_e7jooqy",
            "Comment ID": "e7jr3hf",
            "Author": "cryptogrip",
            "Date Created": "10-10-2018 21:04:15",
            "Upvotes": 3,
            "Text": "No idea where you got those random numbers, or why you sound so in need to share that.\nBut to correct you, interest very much follows price..of course. That's the very defintion of FOMO.",
            "Edited?": false,
            "Is Submitter?": false,
            "Stickied?": false
        }
    ],
    "e7jz37z": [
        {
            "Parent ID": "t1_e7jxhaq",
            "Comment ID": "e7jz37z",
            "Author": "cryptogrip",
            "Date Created": "10-10-2018 23:21:18",
            "Upvotes": 3,
            "Text": "What in the hell are you talking about lol. You mention my name in so many posts all because I'm positive about bakkt. You can put these twist on words all you want but I've never said saviour BS and I sure as hell have never been naive enough to talk this short term about anything. You talk a lot of shit and that's your business. But leave me out of your fantasy land please :).",
            "Edited?": false,
            "Is Submitter?": false,
            "Stickied?": false
        }
    ],
    "e7jz4p2": [
        {
            "Parent ID": "t1_e7jxhaq",
            "Comment ID": "e7jz4p2",
            "Author": "whalecheetah",
            "Date Created": "10-10-2018 23:22:01",
            "Upvotes": 5,
            "Text": "Oh this is a good screenshot for the next ath",
            "Edited?": false,
            "Is Submitter?": false,
            "Stickied?": false
        }
    ],
    "e7jym2o": [
        {
            "Parent ID": "t1_e7jxhaq",
            "Comment ID": "e7jym2o",
            "Author": "curseknight",
            "Date Created": "10-10-2018 23:12:33",
            "Upvotes": 1,
            "Text": "Man, posting FUD must be like sex to this guy. Can't explain it any other way!",
            "Edited?": false,
            "Is Submitter?": false,
            "Stickied?": false
        }
    ],
    "e7jtrva": [
        {
            "Parent ID": "t1_e7jpwjv",
            "Comment ID": "e7jtrva",
            "Author": "p3rk0",
            "Date Created": "10-10-2018 21:49:50",
            "Upvotes": 2,
            "Text": "It\u2019s pretty amazing. A ton of shops accept crypto. ",
            "Edited?": false,
            "Is Submitter?": false,
            "Stickied?": false
        }
    ],
    "e7jyp10": [
        {
            "Parent ID": "t1_e7jx8vi",
            "Comment ID": "e7jyp10",
            "Author": "coloured_sunglasses",
            "Date Created": "10-10-2018 23:14:05",
            "Upvotes": 1,
            "Text": "I sold months ago, I have no stake",
            "Edited?": false,
            "Is Submitter?": false,
            "Stickied?": false
        }
    ],
    "e7jz082": [
        {
            "Parent ID": "t1_e7jx9io",
            "Comment ID": "e7jz082",
            "Author": "[deleted]",
            "Date Created": "10-10-2018 23:19:47",
            "Upvotes": 1,
            "Text": "Dollars ? Forever the slave ? \ud83e\udd2d",
            "Edited?": false,
            "Is Submitter?": false,
            "Stickied?": false
        }
    ],
    "e7juqmt": [
        {
            "Parent ID": "t1_e7jtr6z",
            "Comment ID": "e7juqmt",
            "Author": "whalecheetah",
            "Date Created": "10-10-2018 22:06:28",
            "Upvotes": 1,
            "Text": "hedge funds operate more risk on risk off. it really could be as simple as freeing up cash in the short term. there are always rumors about some exchange and anything tether related ",
            "Edited?": false,
            "Is Submitter?": false,
            "Stickied?": false
        }
    ],
    "e7jv4iu": [
        {
            "Parent ID": "t1_e7jtr6z",
            "Comment ID": "e7jv4iu",
            "Author": "Uberse",
            "Date Created": "10-10-2018 22:12:56",
            "Upvotes": 1,
            "Text": "Those rumors are old news already. Why would everybody act on them now? ",
            "Edited?": false,
            "Is Submitter?": false,
            "Stickied?": false
        }
    ],
    "e7jbk5k": [
        {
            "Parent ID": "t1_e7j8fbp",
            "Comment ID": "e7jbk5k",
            "Author": "cryptogrip",
            "Date Created": "10-10-2018 16:59:06",
            "Upvotes": 8,
            "Text": "How can you price in a product that isn't active yet? If it becomes active, and people start purchasing bitcoin via bakkt and an etf that doesn't run solely on derivitives, then the additional buying will drive the price up. Plus being approved would further legitimize bitcoin and have a positive impact on public sentiment. This can't be priced in like stock projections.",
            "Edited?": false,
            "Is Submitter?": false,
            "Stickied?": false
        }
    ],
    "e7jxj8z": [
        {
            "Parent ID": "t1_e7jxfc0",
            "Comment ID": "e7jxj8z",
            "Author": "ray3400",
            "Date Created": "10-10-2018 22:53:36",
            "Upvotes": 0,
            "Text": "Hope so. I'm not holding, but I want the market to move up by EOY so I can actually make something.",
            "Edited?": false,
            "Is Submitter?": false,
            "Stickied?": false
        }
    ],
    "e7jxg3g": [
        {
            "Parent ID": "t1_e7jw1bh",
            "Comment ID": "e7jxg3g",
            "Author": "ray3400",
            "Date Created": "10-10-2018 22:52:08",
            "Upvotes": 2,
            "Text": "Ok, but wouldn't that be a more gradual drop as the interest goes down? This happened in less than an hour...",
            "Edited?": false,
            "Is Submitter?": false,
            "Stickied?": false
        }
    ],
    "e7k724x": [
        {
            "Parent ID": "t1_e7jw1bh",
            "Comment ID": "e7k724x",
            "Author": "warlord85",
            "Date Created": "10-11-2018 02:18:22",
            "Upvotes": 1,
            "Text": ">the secret trading strategy from 1930's\n\nThe \"market\" realized that and decided to take action in a few seconds? Sounds legit.",
            "Edited?": false,
            "Is Submitter?": false,
            "Stickied?": false
        }
    ],
    "e7k5pit": [
        {
            "Parent ID": "t1_e7jw1bh",
            "Comment ID": "e7k5pit",
            "Author": "RIMS_REAL_BIG",
            "Date Created": "10-11-2018 01:42:18",
            "Upvotes": -1,
            "Text": "Should be a lot lower. ",
            "Edited?": false,
            "Is Submitter?": false,
            "Stickied?": false
        }
    ],
    "e7k9q9w": [
        {
            "Parent ID": "t1_e7k9ixe",
            "Comment ID": "e7k9q9w",
            "Author": "crayzcrinkle",
            "Date Created": "10-11-2018 03:38:36",
            "Upvotes": 1,
            "Text": "Yeah but through coinbase \"fee\" for that would be 3.85% of my deposit. I can bank transfer direct and avoid any fee. Except the 0.003% fee for buying on GDAX.",
            "Edited?": false,
            "Is Submitter?": false,
            "Stickied?": false
        }
    ],
    "e7jtq6f": [
        {
            "Parent ID": "t1_e7jpko1",
            "Comment ID": "e7jtq6f",
            "Author": "riyau_32",
            "Date Created": "10-10-2018 21:49:02",
            "Upvotes": 2,
            "Text": "I can't help but laugh at these sarcastic replies \ud83d\ude02",
            "Edited?": false,
            "Is Submitter?": false,
            "Stickied?": false
        }
    ],
    "e7juimx": [
        {
            "Parent ID": "t1_e7jrxxy",
            "Comment ID": "e7juimx",
            "Author": "FlyGuy74",
            "Date Created": "10-10-2018 22:02:41",
            "Upvotes": 1,
            "Text": "Too soon to call the timing. Check back in a month when he buys back in higher than he sold. ",
            "Edited?": false,
            "Is Submitter?": false,
            "Stickied?": false
        }
    ],
    "e7jh62v": [
        {
            "Parent ID": "t1_e7jg9q6",
            "Comment ID": "e7jh62v",
            "Author": "arBettor",
            "Date Created": "10-10-2018 18:21:13",
            "Upvotes": 4,
            "Text": "Yeah stock market investors have become complacent, so today's drop was pretty jarring.  And many market segments participated in the fall, some of which are seen as noncorrelated or less-correlated: public REITs, commodities, etc.  If BTC can simply continue to stay relatively stable during stock market declines, its attractiveness for institutions will increase.  Modern Portfolio Theory highlights the need for truly uncorrelated assets, and hopefully BTC will continue to prove its value in that sense.",
            "Edited?": false,
            "Is Submitter?": false,
            "Stickied?": false
        }
    ],
    "e7jsbrw": [
        {
            "Parent ID": "t1_e7jrpjn",
            "Comment ID": "e7jsbrw",
            "Author": "arBettor",
            "Date Created": "10-10-2018 21:25:15",
            "Upvotes": 6,
            "Text": "I spoke too soon apparently.\n\nOh well...back to dry dog food.  I'll really miss the cans.",
            "Edited?": false,
            "Is Submitter?": false,
            "Stickied?": false
        }
    ],
    "e7jgg5k": [
        {
            "Parent ID": "t1_e7jfr4i",
            "Comment ID": "e7jgg5k",
            "Author": "arBettor",
            "Date Created": "10-10-2018 18:10:03",
            "Upvotes": 2,
            "Text": "Thanks, just bought 100K.",
            "Edited?": false,
            "Is Submitter?": false,
            "Stickied?": false
        }
    ],
    "e7jtiv3": [
        {
            "Parent ID": "t1_e7jt9i9",
            "Comment ID": "e7jtiv3",
            "Author": "55555",
            "Date Created": "10-10-2018 21:45:33",
            "Upvotes": 1,
            "Text": "Hah, no shit. I bought.",
            "Edited?": false,
            "Is Submitter?": false,
            "Stickied?": false
        }
    ],
    "e7ixsri": [
        {
            "Parent ID": "t1_e7ixli7",
            "Comment ID": "e7ixsri",
            "Author": "55555",
            "Date Created": "10-10-2018 13:53:09",
            "Upvotes": 1,
            "Text": "Well right now i'm a little in the red, because I bought some on that last little run up. I'm thankful I got some before the bubble, but sad that I bought some at 18k.",
            "Edited?": false,
            "Is Submitter?": false,
            "Stickied?": false
        }
    ],
    "e7i8uz3": [
        {
            "Parent ID": "t1_e7i6lr9",
            "Comment ID": "e7i8uz3",
            "Author": "[deleted]",
            "Date Created": "10-10-2018 07:23:30",
            "Upvotes": -1,
            "Text": "[deleted]",
            "Edited?": false,
            "Is Submitter?": false,
            "Stickied?": false
        }
    ],
    "e7ju7jt": [
        {
            "Parent ID": "t1_e7jtxcv",
            "Comment ID": "e7ju7jt",
            "Author": "flunderbossanova",
            "Date Created": "10-10-2018 21:57:20",
            "Upvotes": -2,
            "Text": "Doesn't make it any less of a joke... just means it's a joke that made them some money.",
            "Edited?": false,
            "Is Submitter?": false,
            "Stickied?": false
        }
    ],
    "e7jz0lk": [
        {
            "Parent ID": "t1_e7jysoi",
            "Comment ID": "e7jz0lk",
            "Author": "RIMS_REAL_BIG",
            "Date Created": "10-10-2018 23:19:58",
            "Upvotes": 1,
            "Text": "I like jokes. ",
            "Edited?": false,
            "Is Submitter?": false,
            "Stickied?": false
        }
    ],
    "e7iquz5": [
        {
            "Parent ID": "t1_e7iq9az",
            "Comment ID": "e7iquz5",
            "Author": "[deleted]",
            "Date Created": "10-10-2018 12:18:57",
            "Upvotes": -2,
            "Text": "[deleted]",
            "Edited?": false,
            "Is Submitter?": false,
            "Stickied?": false
        }
    ],
    "e7juemj": [
        {
            "Parent ID": "t1_e7ju6lr",
            "Comment ID": "e7juemj",
            "Author": "apofiissalex",
            "Date Created": "10-10-2018 22:00:47",
            "Upvotes": -1,
            "Text": "By year end! wait) ",
            "Edited?": false,
            "Is Submitter?": false,
            "Stickied?": false
        }
    ],
    "e7jtf41": [
        {
            "Parent ID": "t1_e7jsk4y",
            "Comment ID": "e7jtf41",
            "Author": "bathdweller",
            "Date Created": "10-10-2018 21:43:47",
            "Upvotes": 2,
            "Text": "End of the shorts cycle. Not news based.",
            "Edited?": false,
            "Is Submitter?": false,
            "Stickied?": false
        }
    ],
    "e7jyuw3": [
        {
            "Parent ID": "t1_e7jsk4y",
            "Comment ID": "e7jyuw3",
            "Author": "curseknight",
            "Date Created": "10-10-2018 23:17:04",
            "Upvotes": 1,
            "Text": "If you're going to despair every time a price crash happens, you came to the wrong neighborhood bro",
            "Edited?": false,
            "Is Submitter?": false,
            "Stickied?": false
        }
    ],
    "e7jtgg2": [
        {
            "Parent ID": "t1_e7jsqtl",
            "Comment ID": "e7jtgg2",
            "Author": "RIMS_REAL_BIG",
            "Date Created": "10-10-2018 21:44:24",
            "Upvotes": 0,
            "Text": "Don't worry, it will go lower",
            "Edited?": false,
            "Is Submitter?": false,
            "Stickied?": false
        }
    ],
    "e7k2iel": [
        {
            "Parent ID": "t1_e7k1qww",
            "Comment ID": "e7k2iel",
            "Author": "[deleted]",
            "Date Created": "10-11-2018 00:28:52",
            "Upvotes": 0,
            "Text": "True... but it takes some from whales into the hands of people who want to use it (and they can buy at a discount).",
            "Edited?": false,
            "Is Submitter?": false,
            "Stickied?": false
        }
    ],
    "e7jukiw": [
        {
            "Parent ID": "t1_e7jr3hf",
            "Comment ID": "e7jukiw",
            "Author": "Neveragain646",
            "Date Created": "10-10-2018 22:03:35",
            "Upvotes": -1,
            "Text": "There's not a single product in the world where interest follows the price. You need interest and demand first, then the price goes up. Basic logic. ",
            "Edited?": false,
            "Is Submitter?": false,
            "Stickied?": false
        }
    ],
    "e7jzf5t": [
        {
            "Parent ID": "t1_e7jz4p2",
            "Comment ID": "e7jzf5t",
            "Author": "cryptogrip",
            "Date Created": "10-10-2018 23:27:25",
            "Upvotes": 1,
            "Text": "Ha ha. Man that guy is seriously odd. It's like he takes things super personal as if anyone cares. He could be a 60 year old transexual for all we know lol.",
            "Edited?": false,
            "Is Submitter?": false,
            "Stickied?": false
        }
    ],
    "e7k61zt": [
        {
            "Parent ID": "t1_e7jym2o",
            "Comment ID": "e7k61zt",
            "Author": "damchi",
            "Date Created": "10-11-2018 01:51:18",
            "Upvotes": 1,
            "Text": "Talking crap about bitcoin and spreading FUD is probably the only thing guys like him have to look forward to all day. It's sad actually.\n\nOr they're paid trolls. Then they're just pathetic. ",
            "Edited?": "10-11-2018 04:12:50",
            "Is Submitter?": false,
            "Stickied?": false
        }
    ],
    "e7kv5o3": [
        {
            "Parent ID": "t1_e7jym2o",
            "Comment ID": "e7kv5o3",
            "Author": "xelephonte",
            "Date Created": "10-11-2018 11:33:09",
            "Upvotes": 1,
            "Text": "Guys I don\u2019t control the crypto Bitcoin market, so don\u2019t blame me. I don\u2019t create FUD, the whales do, the markets do. I have every right to make a Bitcoin prediction based on historical figures whether it\u2019s FOMO or FUD. And my FUD has been far more accurate than Cryptogrip\u2019s baseless FOMO over the stupid Bakkt hype he\u2019s been stroking himself to. I\u2019m a realist, cryptogrip isn\u2019t. Cryptogrip thinks Bitcoin will hit $100K by end of 2018 and we will be driving flying Lambos to the moon. Listen to cryptogrip and you will be homeless pushing a stolen shopping cart till you\u2019re 6 feet under. That is all.",
            "Edited?": false,
            "Is Submitter?": false,
            "Stickied?": false
        }
    ],
    "e7k2t1b": [
        {
            "Parent ID": "t1_e7jyp10",
            "Comment ID": "e7k2t1b",
            "Author": "flunderbossanova",
            "Date Created": "10-11-2018 00:35:10",
            "Upvotes": -2,
            "Text": "Enjoy your wealth, man, hopefully you made a tidy profit!",
            "Edited?": false,
            "Is Submitter?": false,
            "Stickied?": false
        }
    ],
    "e7juvrl": [
        {
            "Parent ID": "t1_e7juqmt",
            "Comment ID": "e7juvrl",
            "Author": "flunderbossanova",
            "Date Created": "10-10-2018 22:08:51",
            "Upvotes": 1,
            "Text": "is there any proof that hedge funds are actually buying bitcoin?",
            "Edited?": false,
            "Is Submitter?": false,
            "Stickied?": false
        }
    ],
    "e7jxn89": [
        {
            "Parent ID": "t1_e7jv4iu",
            "Comment ID": "e7jxn89",
            "Author": "tbonecollion",
            "Date Created": "10-10-2018 22:55:32",
            "Upvotes": 2,
            "Text": "Whales are bored and need more money.",
            "Edited?": false,
            "Is Submitter?": false,
            "Stickied?": false
        }
    ],
    "e7jw2bh": [
        {
            "Parent ID": "t1_e7jv4iu",
            "Comment ID": "e7jw2bh",
            "Author": "flunderbossanova",
            "Date Created": "10-10-2018 22:28:34",
            "Upvotes": 1,
            "Text": "UDST/USD keeps on slipping",
            "Edited?": false,
            "Is Submitter?": false,
            "Stickied?": false
        }
    ],
    "e7kv1mp": [
        {
            "Parent ID": "t1_e7jtq6f",
            "Comment ID": "e7kv1mp",
            "Author": "[deleted]",
            "Date Created": "10-11-2018 11:31:37",
            "Upvotes": 1,
            "Text": "Lol it dropped bad today I think I made a good call",
            "Edited?": false,
            "Is Submitter?": false,
            "Stickied?": false
        }
    ],
    "e7q9dnb": [
        {
            "Parent ID": "t1_e7jsbrw",
            "Comment ID": "e7q9dnb",
            "Author": "Nemesis207",
            "Date Created": "10-13-2018 23:12:55",
            "Upvotes": 2,
            "Text": "lol now that's damn funny man. Shit, crypto has made a liar out of EVERYONE at one point or another...",
            "Edited?": false,
            "Is Submitter?": false,
            "Stickied?": false
        }
    ],
    "e7jizyp": [
        {
            "Parent ID": "t1_e7jgg5k",
            "Comment ID": "e7jizyp",
            "Author": "AussieBitcoiner",
            "Date Created": "10-10-2018 18:49:55",
            "Upvotes": 1,
            "Text": "just went all-in on honey jars myself.\n\nThough they may be slightly correlated to your sandwiches. ",
            "Edited?": false,
            "Is Submitter?": false,
            "Stickied?": false
        }
    ],
    "e7iyb7a": [
        {
            "Parent ID": "t1_e7ixsri",
            "Comment ID": "e7iyb7a",
            "Author": "Spykwak",
            "Date Created": "10-10-2018 14:00:05",
            "Upvotes": 3,
            "Text": "Try to not act on emotion. \n\nDepending on the % of your wealth you have in the game you can ride this one out, try to reduce your exposure if we reach your breakeven point, or sell at a loss if you don\u2019t believe we are going to recover from this point.",
            "Edited?": false,
            "Is Submitter?": false,
            "Stickied?": false
        }
    ],
    "e7i8y04": [
        {
            "Parent ID": "t1_e7i8uz3",
            "Comment ID": "e7i8y04",
            "Author": "lesterdesa",
            "Date Created": "10-10-2018 07:25:44",
            "Upvotes": -1,
            "Text": "tonight you need to save yourself so BTC pumps",
            "Edited?": false,
            "Is Submitter?": false,
            "Stickied?": false
        }
    ],
    "e7jvs9r": [
        {
            "Parent ID": "t1_e7ju7jt",
            "Comment ID": "e7jvs9r",
            "Author": "Coinosphere",
            "Date Created": "10-10-2018 22:23:54",
            "Upvotes": 3,
            "Text": "And the joke just keeps on earning higher and higher returns for anyone who dares to zoom out.",
            "Edited?": false,
            "Is Submitter?": false,
            "Stickied?": false
        }
    ],
    "e7isns0": [
        {
            "Parent ID": "t1_e7iquz5",
            "Comment ID": "e7isns0",
            "Author": "[deleted]",
            "Date Created": "10-10-2018 12:43:31",
            "Upvotes": 2,
            "Text": "[deleted]",
            "Edited?": false,
            "Is Submitter?": false,
            "Stickied?": false
        }
    ],
    "e7k24a3": [
        {
            "Parent ID": "t1_e7jyuw3",
            "Comment ID": "e7k24a3",
            "Author": "riyau_32",
            "Date Created": "10-11-2018 00:20:37",
            "Upvotes": 0,
            "Text": "haa no",
            "Edited?": false,
            "Is Submitter?": false,
            "Stickied?": false
        }
    ],
    "e7jtra8": [
        {
            "Parent ID": "t1_e7jtgg2",
            "Comment ID": "e7jtra8",
            "Author": "The-Physicist",
            "Date Created": "10-10-2018 21:49:33",
            "Upvotes": 1,
            "Text": "You think? Support at ~$6,100 seems robust so far. ",
            "Edited?": false,
            "Is Submitter?": false,
            "Stickied?": false
        }
    ],
    "e7k8yi8": [
        {
            "Parent ID": "t1_e7k2iel",
            "Comment ID": "e7k8yi8",
            "Author": "maxtbag",
            "Date Created": "10-11-2018 03:13:15",
            "Upvotes": 2,
            "Text": "This is just a whale dumping so he can buy back more at lower prices after all the sheep are done selling at the bottom. Which in fact concentrates btc further into the hands of the few, it doesn't spread it out. ",
            "Edited?": false,
            "Is Submitter?": false,
            "Stickied?": false
        }
    ],
    "e7jzkxj": [
        {
            "Parent ID": "t1_e7jukiw",
            "Comment ID": "e7jzkxj",
            "Author": "cryptogrip",
            "Date Created": "10-10-2018 23:30:26",
            "Upvotes": 2,
            "Text": "F.O.M.O. ",
            "Edited?": false,
            "Is Submitter?": false,
            "Stickied?": false
        }
    ],
    "e7k03l3": [
        {
            "Parent ID": "t1_e7jzf5t",
            "Comment ID": "e7k03l3",
            "Author": "whalecheetah",
            "Date Created": "10-10-2018 23:40:18",
            "Upvotes": 1,
            "Text": "Seems like we always have a few of those floating around in here. They get worked up every time the market goes down a couple points. I don't think they really stick around Bitcoin very long. It seems like most of them get really frustrated with it and leave then hope it all Burns to the ground",
            "Edited?": false,
            "Is Submitter?": false,
            "Stickied?": false
        }
    ],
    "e7jva7d": [
        {
            "Parent ID": "t1_e7juvrl",
            "Comment ID": "e7jva7d",
            "Author": "whalecheetah",
            "Date Created": "10-10-2018 22:15:33",
            "Upvotes": 1,
            "Text": "They are open to buy whatever they want. Some of the more famous are people like Mike novogratz and his fund there are plenty of smaller ones likely doing the same thing. Positions are often kept secret until they decide to Market what they have. It's just really Suspect with the heavy distribution in the S&P 500 today. \n\n",
            "Edited?": false,
            "Is Submitter?": false,
            "Stickied?": false
        }
    ],
    "e7jxc5g": [
        {
            "Parent ID": "t1_e7jw2bh",
            "Comment ID": "e7jxc5g",
            "Author": "Uberse",
            "Date Created": "10-10-2018 22:50:13",
            "Upvotes": 1,
            "Text": "Slipping or crashing? ",
            "Edited?": false,
            "Is Submitter?": false,
            "Stickied?": false
        }
    ],
    "e7jvlc8": [
        {
            "Parent ID": "t1_e7jizyp",
            "Comment ID": "e7jvlc8",
            "Author": "destruct1001",
            "Date Created": "10-10-2018 22:20:41",
            "Upvotes": 1,
            "Text": "Honey jars are better then sandwiches as they don't go bad as fast.\nAll in honey jars!",
            "Edited?": false,
            "Is Submitter?": false,
            "Stickied?": false
        }
    ],
    "e7iyr0c": [
        {
            "Parent ID": "t1_e7iyb7a",
            "Comment ID": "e7iyr0c",
            "Author": "55555",
            "Date Created": "10-10-2018 14:06:02",
            "Upvotes": 3,
            "Text": "Since I decided to get in, my plan has always been to get more BTC. It's just that i'm as committed as I want to be right now. ",
            "Edited?": false,
            "Is Submitter?": false,
            "Stickied?": false
        }
    ],
    "e7jxlem": [
        {
            "Parent ID": "t1_e7jvs9r",
            "Comment ID": "e7jxlem",
            "Author": "tbonecollion",
            "Date Created": "10-10-2018 22:54:40",
            "Upvotes": 2,
            "Text": "Everything is a joke lifes a joke. WHy sit around and cry about it get in or stay out. Cry because the price goes up to fast cry because the price is to low. WTF. Stocks are crashing BTC is a joke. Like I said everything is a joke.",
            "Edited?": false,
            "Is Submitter?": false,
            "Stickied?": false
        }
    ],
    "e7jw0xa": [
        {
            "Parent ID": "t1_e7jvs9r",
            "Comment ID": "e7jw0xa",
            "Author": "flunderbossanova",
            "Date Created": "10-10-2018 22:27:56",
            "Upvotes": 1,
            "Text": "Don't zoom out too far though",
            "Edited?": false,
            "Is Submitter?": false,
            "Stickied?": false
        }
    ],
    "e7jwluz": [
        {
            "Parent ID": "t1_e7jvs9r",
            "Comment ID": "e7jwluz",
            "Author": "The-Physicist",
            "Date Created": "10-10-2018 22:37:41",
            "Upvotes": 1,
            "Text": "Hoping that\u2019s me soon \ud83e\udd11",
            "Edited?": false,
            "Is Submitter?": false,
            "Stickied?": false
        }
    ],
    "e7ka3e7": [
        {
            "Parent ID": "t1_e7jvs9r",
            "Comment ID": "e7ka3e7",
            "Author": "bathdweller",
            "Date Created": "10-11-2018 03:51:11",
            "Upvotes": 0,
            "Text": "That depends on when a given person bought.",
            "Edited?": false,
            "Is Submitter?": false,
            "Stickied?": false
        }
    ],
    "e7itaif": [
        {
            "Parent ID": "t1_e7isns0",
            "Comment ID": "e7itaif",
            "Author": "[deleted]",
            "Date Created": "10-10-2018 12:52:05",
            "Upvotes": -3,
            "Text": "[deleted]",
            "Edited?": false,
            "Is Submitter?": false,
            "Stickied?": false
        }
    ],
    "e7k2bvj": [
        {
            "Parent ID": "t1_e7k24a3",
            "Comment ID": "e7k2bvj",
            "Author": "riyau_32",
            "Date Created": "10-11-2018 00:25:01",
            "Upvotes": 1,
            "Text": "curiosity doesn't mean despair",
            "Edited?": false,
            "Is Submitter?": false,
            "Stickied?": false
        }
    ],
    "e7k0l0z": [
        {
            "Parent ID": "t1_e7k03l3",
            "Comment ID": "e7k0l0z",
            "Author": "cryptogrip",
            "Date Created": "10-10-2018 23:49:35",
            "Upvotes": 0,
            "Text": "Yeah. It's as though they feel like they've won something... almost like they've accomplished something because bitcoin price went down. I couldn't care less, this is a long term thing and I've always had that stance. I just think bakkt is one of the positive steps along the way. He disagrees lol.",
            "Edited?": false,
            "Is Submitter?": false,
            "Stickied?": false
        }
    ],
    "e7iyzqz": [
        {
            "Parent ID": "t1_e7iyr0c",
            "Comment ID": "e7iyzqz",
            "Author": "Spykwak",
            "Date Created": "10-10-2018 14:09:20",
            "Upvotes": 3,
            "Text": "Ok, then if you still have some liquidity you can increase your position since we are below/around your breakeven point :-)",
            "Edited?": false,
            "Is Submitter?": false,
            "Stickied?": false
        }
    ],
    "e7kf5jf": [
        {
            "Parent ID": "t1_e7jw0xa",
            "Comment ID": "e7kf5jf",
            "Author": "Coinosphere",
            "Date Created": "10-11-2018 06:47:17",
            "Upvotes": 1,
            "Text": "Why not? ",
            "Edited?": false,
            "Is Submitter?": false,
            "Stickied?": false
        }
    ],
    "e7kezro": [
        {
            "Parent ID": "t1_e7ka3e7",
            "Comment ID": "e7kezro",
            "Author": "Coinosphere",
            "Date Created": "10-11-2018 06:42:59",
            "Upvotes": 2,
            "Text": "Not with bitcoin it doesn't. There is no 3 year period in Bitcoin's life that wasn't a massive gain. \n\nIf not for the only major exchange being hacked to pieces in 2014, there wouldn't even be a 2-year period that could say the same.",
            "Edited?": false,
            "Is Submitter?": false,
            "Stickied?": false
        }
    ],
    "e7j1uac": [
        {
            "Parent ID": "t1_e7itaif",
            "Comment ID": "e7j1uac",
            "Author": "Rattlesnake_Mullet",
            "Date Created": "10-10-2018 14:47:33",
            "Upvotes": 4,
            "Text": "There is nothing more decentralized than bitcoin at the moment. Don't understand your critique, if serious.",
            "Edited?": false,
            "Is Submitter?": false,
            "Stickied?": false
        }
    ],
    "e7k14un": [
        {
            "Parent ID": "t1_e7k0l0z",
            "Comment ID": "e7k14un",
            "Author": "whalecheetah",
            "Date Created": "10-11-2018 00:00:28",
            "Upvotes": 1,
            "Text": "That's why we stick around and he's not going to be. I saw the market sell-off tonight first thing I thought is hey I should throw another hundred bucks at this. Popped off at 6200. Didn't even think twice and didn't even care that it went a little bit lower. Sitting around playing a little Destiny 2 now and not even thinking about it. A lot of us do stuff like that on a weekly basis. Some people just can't handle it and they freak out. Dump then hate",
            "Edited?": false,
            "Is Submitter?": false,
            "Stickied?": false
        }
    ],
    "e7kf54h": [
        {
            "Parent ID": "t1_e7kezro",
            "Comment ID": "e7kf54h",
            "Author": "bathdweller",
            "Date Created": "10-11-2018 06:46:58",
            "Upvotes": 2,
            "Text": "Sounds #unsinkable to me.",
            "Edited?": false,
            "Is Submitter?": false,
            "Stickied?": false
        }
    ],
    "e7j2quc": [
        {
            "Parent ID": "t1_e7j1uac",
            "Comment ID": "e7j2quc",
            "Author": "admiralCeres",
            "Date Created": "10-10-2018 14:59:44",
            "Upvotes": 6,
            "Text": "sounds like he's leaving because he's anticipating billions of dollars coming into the space, and wants to get out before the price goes up. Strange reasoning.",
            "Edited?": false,
            "Is Submitter?": false,
            "Stickied?": false
        }
    ],
    "e7k3aan": [
        {
            "Parent ID": "t1_e7k14un",
            "Comment ID": "e7k3aan",
            "Author": "cryptogrip",
            "Date Created": "10-11-2018 00:45:24",
            "Upvotes": 1,
            "Text": "Yes. Exactly.",
            "Edited?": false,
            "Is Submitter?": false,
            "Stickied?": false
        }
    ],
    "e7jc115": [
        {
            "Parent ID": "t1_e7j2quc",
            "Comment ID": "e7jc115",
            "Author": "8w2e5s6h8r6a5n9e0a3s",
            "Date Created": "10-10-2018 17:05:39",
            "Upvotes": 2,
            "Text": "agreed",
            "Edited?": false,
            "Is Submitter?": false,
            "Stickied?": false
        }
    ]
}